{
  "T4-B101-2": [
    "T4-B100-8",
    "T4-B100-4"
  ],
  "T4-B109": [
    "T4-B100-8",
    "T4-B100-4"
  ],
  "T4-B102": [
    "T4-B100-6",
    "T4-B100-3"
  ],
  "T4-B101-1": [
    "T4-B100-4",
    "T4-B100-5"
  ],
  "T4-B104": [
    "T4-B100-3",
    "T4-B100-6"
  ],
  "T4-B103": [
    "T4-B100-3",
    "T4-B100-6"
  ],
  "T4-B105": [
    "T4-B100-2",
    "T4-B100-1"
  ],
  "T4-B106": [
    "T4-B100-2",
    "T4-B100-1"
  ],
  "T4-B107": [
    "T4-B100-1",
    "T4-B100-9"
  ],
  "RB-B103-1": [
    "RB-B100-1",
    "RB-B100-2"
  ],
  "RB-B103": [
    "RB-B100-1",
    "RB-B100-2"
  ],
  "RB-B101": [
    "RB-B100-4",
    "RB-B100-3"
  ],
  "RB-B104": [
    "RB-B100-3",
    "RB-B100-4"
  ],
  "RB-B102": [
    "RB-B100-2",
    "RB-B100-1"
  ],
  "RB-B106": [
    "RB-B100-2",
    "RB-B100-1"
  ],
  "RB-Stack-B1F": [
    "RB-Stack-B100-1"
  ],
  "RB-B104-1": [
    "RB-B100-3",
    "RB-B100-2"
  ],
  "RB-B105": [
    "RB-B100-4",
    "RB-B100-3"
  ],
  "T4-B108": [
    "T4-B100-6",
    "T4-B100-5"
  ],
  "T4-B110": [
    "T4-B100-9",
    "T4-B100-10"
  ],
  "T4-B111": [
    "T4-B100-10",
    "T4-B100-9"
  ],
  "T4-B112": [
    "T4-B100-10",
    "T4-B100-9"
  ],
  "RB-205": [
    "RB-200-1",
    "RB-200-3"
  ],
  "T4-204": [
    "T4-200-2",
    "T4-200-3"
  ],
  "T4-203-2": [
    "T4-200-2",
    "T4-200-3"
  ],
  "T4-203-1": [
    "T4-200-2",
    "T4-200-1"
  ],
  "T4-201-2": [
    "T4-200-1",
    "T4-200-2"
  ],
  "T4-201-1": [
    "T4-200-1",
    "T4-200-2"
  ],
  "T4-202-2": [
    "T4-200-2",
    "T4-200-1"
  ],
  "T4-202-1": [
    "T4-200-1",
    "T4-200-2"
  ],
  "T4-205-2": [
    "T4-200-4",
    "T4-200-3"
  ],
  "T4-205-1": [
    "T4-200-4",
    "T4-200-3"
  ],
  "T4-206": [
    "T4-200-4",
    "T4-200-3"
  ],
  "T1-201": [
    "T1-200-1",
    "T1-200-2"
  ],
  "T1-202-1": [
    "T1-200-2",
    "T1-200-1"
  ],
  "T1-202-2": [
    "T1-200-2",
    "T1-200-1"
  ],
  "T1-203-1": [
    "T1-200-2",
    "T1-200-1"
  ],
  "T1-203-2": [
    "T1-200-2",
    "T1-200-3"
  ],
  "T1-205-1": [
    "T1-200-3",
    "T1-200-2"
  ],
  "T1-205-2": [
    "T1-200-3",
    "T1-200-2"
  ],
  "T1-206": [
    "T1-200-3",
    "T1-200-2"
  ],
  "RB-203": [
    "RB-200-2",
    "RB-200-3"
  ],
  "RB-201-1": [
    "RB-200-2",
    "RB-200-3"
  ],
  "RB-202": [
    "RB-200-2",
    "RB-200-3"
  ],
  "RB-204": [
    "RB-200-3",
    "RB-200-1"
  ],
  "T1-204-1": [
    "T1-200-2",
    "T1-200-3"
  ],
  "T1-204-2": [
    "T1-200-3",
    "T1-200-2"
  ],
  "T1-201-1": [
    "T1-200-1",
    "T1-200-2"
  ],
  "T1-201-2": [
    "T1-200-2",
    "T1-200-1"
  ],
  "T4-WCM-2F": [
    "T4-200-4",
    "T4-200-3"
  ],
  "T4-WCF-2F": [
    "T4-200-3",
    "T4-200-4"
  ],
  "RB-Stack-2F": [
    "RB-Stack-200-1",
    "RB-Stack-200-2"
  ],
  "T1-101-4": [
    "T1-100-1",
    "T1-100-2"
  ],
  "T1-101-1": [
    "T1-100-1",
    "T1-100-2"
  ],
  "RB-Stack-1F": [
    "RB-Stack-100-1",
    "RB-Stack-100-2"
  ],
  "AU-101-5": [
    "AU-100-7",
    "AU-100-6"
  ],
  "AU-101-3": [
    "AU-100-4",
    "AU-100-3"
  ],
  "RB-101-1": [
    "RB-100-9",
    "RB-100-10"
  ],
  "RB-103": [
    "RB-100-13",
    "RB-100-8"
  ],
  "RB-104": [
    "RB-100-8",
    "RB-100-6"
  ],
  "RB-WCM-1F": [
    "RB-100-7",
    "RB-100-6"
  ],
  "RB-WCF-1F": [
    "RB-100-6",
    "RB-100-8"
  ],
  "RB-WCM2-1F": [
    "RB-100-11",
    "RB-100-10"
  ],
  "RB-WCF2-1F": [
    "RB-100-10",
    "RB-100-11"
  ],
  "T4-WCM-1F": [
    "T4-100-7",
    "T4-100-3"
  ],
  "T4-WCF-1F": [
    "T4-100-7",
    "T4-100-2"
  ],
  "T1-104": [
    "T1-100-3",
    "T1-100-4"
  ],
  "T1-103-1": [
    "T1-100-3",
    "T1-100-2"
  ],
  "T1-103": [
    "T1-100-2",
    "T1-100-3"
  ],
  "T1-101": [
    "T1-100-1",
    "T1-100-2"
  ],
  "T1-101-2": [
    "T1-100-2",
    "T1-100-1"
  ],
  "T1-101-3": [
    "T1-100-2",
    "T1-100-1"
  ],
  "T1-102": [
    "T1-100-2",
    "T1-100-3"
  ],
  "T1-105": [
    "T1-100-3",
    "T1-100-4"
  ],
  "T1-105-1": [
    "T1-100-4",
    "T1-100-3"
  ],
  "RB-102": [
    "RB-100-14",
    "RB-100-7"
  ],
  "RB-102-1": [
    "RB-100-15",
    "RB-100-14"
  ],
  "RB-102-2": [
    "RB-100-13",
    "RB-100-1"
  ],
  "RB-102-3": [
    "RB-100-13",
    "RB-100-1"
  ],
  "RB-102-4": [
    "RB-100-13",
    "RB-100-1"
  ],
  "RB-101": [
    "RB-100-2",
    "RB-100-1"
  ],
  "RB-101-3": [
    "RB-100-11",
    "RB-100-10"
  ],
  "RB-101-4": [
    "RB-100-13",
    "RB-100-1"
  ],
  "RB-101-2": [
    "RB-100-1",
    "RB-100-2"
  ],
  "AU-101-1": [
    "AU-100-2",
    "AU-100-3"
  ],
  "AU-101-2": [
    "AU-100-6",
    "AU-100-5"
  ],
  "AU-101-4": [
    "AU-100-1",
    "AU-100-2"
  ],
  "T1-301-3": [
    "T1-300-1",
    "T1-300-2"
  ],
  "T1-301": [
    "T1-300-1",
    "T1-300-2"
  ],
  "T1-301-1": [
    "T1-300-1",
    "T1-300-2"
  ],
  "T1-301-2": [
    "T1-300-1",
    "T1-300-2"
  ],
  "T1-302-1": [
    "T1-300-2",
    "T1-300-1"
  ],
  "T1-302-2": [
    "T1-300-2",
    "T1-300-1"
  ],
  "T1-303-1": [
    "T1-300-2",
    "T1-300-1"
  ],
  "T1-303-2": [
    "T1-300-2",
    "T1-300-3"
  ],
  "T1-304-1": [
    "T1-300-2",
    "T1-300-3"
  ],
  "T1-304-2": [
    "T1-300-3",
    "T1-300-2"
  ],
  "T1-305": [
    "T1-300-3",
    "T1-300-2"
  ],
  "T1-306": [
    "T1-300-3",
    "T1-300-2"
  ],
  "T1-307": [
    "T1-300-3",
    "T1-300-2"
  ],
  "T1-308": [
    "T1-300-3",
    "T1-300-2"
  ],
  "T4-307": [
    "T4-300-3",
    "T4-300-2"
  ],
  "T4-306": [
    "T4-300-3",
    "T4-300-2"
  ],
  "T4-305-2": [
    "T4-300-2",
    "T4-300-3"
  ],
  "T4-305-1": [
    "T4-300-2",
    "T4-300-3"
  ],
  "T4-304-2": [
    "T4-300-2",
    "T4-300-3"
  ],
  "T4-304-1": [
    "T4-300-2",
    "T4-300-1"
  ],
  "T4-303-2": [
    "T4-300-2",
    "T4-300-1"
  ],
  "T4-303-1": [
    "T4-300-1",
    "T4-300-2"
  ],
  "T4-302-2": [
    "T4-300-1",
    "T4-300-2"
  ],
  "T4-302-1": [
    "T4-300-1",
    "T4-300-2"
  ],
  "T4-301-2": [
    "T4-300-1",
    "T4-300-2"
  ],
  "T4-301-1": [
    "T4-300-1",
    "T4-300-2"
  ],
  "T4-WCM-3F": [
    "T4-300-3",
    "T4-300-2"
  ],
  "T4-WCF-3F": [
    "T4-300-2",
    "T4-300-3"
  ],
  "RB-Stack-3F": [
    "RB-Stack-300-1",
    "RB-Stack-300-2"
  ],
  "T1-401-1": [
    "T1-400-1",
    "T1-402-1"
  ],
  "RB-308-1": [
    "RB-308",
    "RB-300-1"
  ],
  "RB-308-2": [
    "RB-308",
    "RB-300-1"
  ],
  "RB-309-2": [
    "RB-308",
    "RB-300-1"
  ],
  "RB-309-1": [
    "RB-300-3",
    "RB-300-4"
  ],
  "RB-304-1": [
    "RB-304",
    "RB-300-6"
  ],
  "RB-305": [
    "RB-304",
    "RB-308"
  ],
  "RB-303": [
    "RB-300-4",
    "RB-300-3"
  ],
  "RB-303-1": [
    "RB-300-4",
    "RB-300-3"
  ],
  "RB-WCF-3F": [
    "RB-300-6",
    "RB-304"
  ],
  "RB-WCM-3F": [
    "RB-300-4",
    "RB-300-3"
  ],
  "RB-310": [
    "RB-300-4",
    "RB-300-3"
  ],
  "RB-310-1": [
    "RB-300-4",
    "RB-300-5"
  ],
  "RB-310-2": [
    "RB-300-4",
    "RB-300-3"
  ],
  "RB-304-2": [
    "RB-304",
    "RB-300-6"
  ],
  "RB-304-3": [
    "RB-300-6",
    "RB-304"
  ],
  "RB-304-3-1": [
    "RB-300-6",
    "RB-304"
  ],
  "RB-308-3": [
    "RB-308",
    "RB-300-1"
  ],
  "RB-307-3": [
    "RB-307",
    "RB-300-2"
  ],
  "RB-307-1": [
    "RB-307",
    "RB-300-2"
  ],
  "RB-307-2": [
    "RB-307",
    "RB-300-2"
  ],
  "RB-306-1": [
    "RB-306",
    "RB-300-2"
  ],
  "RB-306-2": [
    "RB-306",
    "RB-300-2"
  ],
  "T1-410-2": [
    "T1-410-7",
    "T1-410-6"
  ],
  "T1-410-3": [
    "T1-410-6",
    "T1-400-2"
  ],
  "T1-410-4": [
    "T1-410-6",
    "T1-400-2"
  ],
  "T1-410-5": [
    "T1-410-6",
    "T1-400-2"
  ],
  "T1-410-1": [
    "T1-410-7",
    "T1-409-1"
  ],
  "T1-409": [
    "T1-409-1",
    "T1-410-7"
  ],
  "T1-408": [
    "T1-408-1",
    "T1-409-1"
  ],
  "T1-407": [
    "T1-407-1",
    "T1-408-1"
  ],
  "T1-406": [
    "T1-406-1",
    "T1-405-1"
  ],
  "T1-405": [
    "T1-405-1",
    "T1-406-1"
  ],
  "T1-404": [
    "T1-404-1",
    "T1-403-1"
  ],
  "T1-403": [
    "T1-403-1",
    "T1-404-1"
  ],
  "T1-402": [
    "T1-402-1",
    "T1-400-1"
  ],
  "T1-401": [
    "T1-402-1",
    "T1-400-1"
  ],
  "T4-407": [
    "T4-400-3",
    "T4-400-2"
  ],
  "T4-406": [
    "T4-400-3",
    "T4-400-2"
  ],
  "T4-WCM-4F": [
    "T4-400-3",
    "T4-400-2"
  ],
  "T4-WCF-4F": [
    "T4-400-2",
    "T4-400-3"
  ],
  "T4-405-2": [
    "T4-400-2",
    "T4-400-3"
  ],
  "T4-405-1": [
    "T4-400-2",
    "T4-400-3"
  ],
  "T4-404-2": [
    "T4-400-2",
    "T4-400-3"
  ],
  "T4-404-1": [
    "T4-400-2",
    "T4-400-1"
  ],
  "T4-403-2": [
    "T4-400-2",
    "T4-400-1"
  ],
  "T4-403-1": [
    "T4-400-1",
    "T4-400-2"
  ],
  "T4-402-2": [
    "T4-400-1",
    "T4-400-2"
  ],
  "T4-402-1": [
    "T4-400-1",
    "T4-400-2"
  ],
  "T4-401-1": [
    "T4-400-1",
    "T4-400-2"
  ],
  "T4-401": [
    "T4-400-1",
    "T4-400-2"
  ],
  "RB-306-3": [
    "RB-306",
    "RB-300-2"
  ],
  "RB-Stack-4F": [
    "RB-Stack-400-1",
    "RB-Stack-400-2"
  ],
  "RB-401-1": [
    "RB-400-2",
    "RB-400-1"
  ],
  "RB-WCF-4F": [
    "RB-400-1",
    "RB-400-5"
  ],
  "RB-WCM-4F": [
    "RB-400-5",
    "RB-400-1"
  ],
  "RB-411-1": [
    "RB-400-6",
    "RB-400-5"
  ],
  "RB-404": [
    "RB-400-3",
    "RB-400-2"
  ],
  "T4-517-3": [
    "T4-500-3",
    "T4-500-2"
  ],
  "T4-517-1": [
    "T4-500-3",
    "T4-500-2"
  ],
  "T4-516-2": [
    "T4-500-3",
    "T4-500-2"
  ],
  "T4-501": [
    "T4-500-1",
    "T4-500-2"
  ],
  "T4-502": [
    "T4-500-1",
    "T4-500-2"
  ],
  "T4-503": [
    "T4-500-1",
    "T4-500-2"
  ],
  "T4-504": [
    "T4-500-1",
    "T4-500-2"
  ],
  "T4-505": [
    "T4-500-1",
    "T4-500-2"
  ],
  "T4-506": [
    "T4-500-1",
    "T4-500-2"
  ],
  "T4-507": [
    "T4-500-1",
    "T4-500-2"
  ],
  "T4-508": [
    "T4-500-2",
    "T4-500-1"
  ],
  "T4-509": [
    "T4-500-2",
    "T4-500-1"
  ],
  "T4-510": [
    "T4-500-2",
    "T4-500-1"
  ],
  "T4-511": [
    "T4-500-2",
    "T4-500-1"
  ],
  "T4-512": [
    "T4-500-2",
    "T4-500-3"
  ],
  "T4-513": [
    "T4-500-2",
    "T4-500-3"
  ],
  "T4-514": [
    "T4-500-2",
    "T4-500-3"
  ],
  "T4-515": [
    "T4-500-2",
    "T4-500-3"
  ],
  "T4-516-1": [
    "T4-500-3",
    "T4-500-2"
  ],
  "T4-517": [
    "T4-500-3",
    "T4-500-2"
  ],
  "T4-517-2": [
    "T4-500-3",
    "T4-500-2"
  ],
  "T4-WCM-5F": [
    "T4-500-3",
    "T4-500-2"
  ],
  "T4-WCF-5F": [
    "T4-500-2",
    "T4-500-3"
  ],
  "RB-401": [
    "RB-400-2",
    "RB-400-1"
  ],
  "RB-402": [
    "RB-400-2",
    "RB-400-3"
  ],
  "RB-403": [
    "RB-400-2",
    "RB-400-3"
  ],
  "RB-405": [
    "RB-400-2",
    "RB-400-3"
  ],
  "RB-406": [
    "RB-400-2",
    "RB-400-3"
  ],
  "RB-405-1": [
    "RB-400-2",
    "RB-400-3"
  ],
  "RB-407": [
    "RB-400-6",
    "RB-400-5"
  ],
  "RB-408": [
    "RB-400-6",
    "RB-400-5"
  ],
  "RB-409": [
    "RB-400-6",
    "RB-400-7"
  ],
  "RB-410": [
    "RB-400-1",
    "RB-400-5"
  ],
  "RB-411": [
    "RB-400-6",
    "RB-400-5"
  ],
  "RB-412": [
    "RB-400-7",
    "RB-400-6"
  ],
  "RB-412-1": [
    "RB-400-6",
    "RB-400-7"
  ],
  "RB-Stack-5F": [
    "RB-Stack-500-2",
    "RB-Stack-500-1"
  ],
  "RB-Stack-6F": [
    "RB-Stack-600-2",
    "RB-Stack-600-1"
  ],
  "T4-605-1": [
    "T4-600-2",
    "T4-600-3"
  ],
  "T4-603-1": [
    "T4-600-1",
    "T4-600-2"
  ],
  "T4-603-2": [
    "T4-600-2",
    "T4-600-1"
  ],
  "RB-507": [
    "RB-500-2",
    "RB-500-3"
  ],
  "RB-WCF-5F": [
    "RB-500-1",
    "RB-500-4"
  ],
  "RB-WCM-5F": [
    "RB-500-4",
    "RB-500-1"
  ],
  "RB-506": [
    "RB-500-4",
    "RB-500-5"
  ],
  "RB-501-1": [
    "RB-500-4",
    "RB-500-5"
  ],
  "RB-501": [
    "RB-500-5",
    "RB-500-4"
  ],
  "RB-505": [
    "RB-500-5",
    "RB-500-4"
  ],
  "RB-504-1": [
    "RB-500-5",
    "RB-500-6"
  ],
  "RB-502": [
    "RB-500-5",
    "RB-500-6"
  ],
  "RB-503": [
    "RB-500-5",
    "RB-500-6"
  ],
  "RB-503-1": [
    "RB-500-6",
    "RB-500-5"
  ],
  "RB-504": [
    "RB-500-6",
    "RB-500-5"
  ],
  "RB-501-2": [
    "RB-500-4",
    "RB-500-1"
  ],
  "RB-508": [
    "RB-500-2",
    "RB-500-3"
  ],
  "RB-509": [
    "RB-500-2",
    "RB-500-3"
  ],
  "RB-510": [
    "RB-500-2",
    "RB-500-1"
  ],
  "RB-Stack-7F": [
    "RB-Stack-700-1"
  ],
  "RB-507-1": [
    "RB-500-2",
    "RB-500-1"
  ],
  "T4-601-1": [
    "T4-600-1",
    "T4-600-2"
  ],
  "T4-601-2": [
    "T4-600-1",
    "T4-600-2"
  ],
  "T4-602-1": [
    "T4-600-1",
    "T4-600-2"
  ],
  "T4-602-2": [
    "T4-600-1",
    "T4-600-2"
  ],
  "T4-604": [
    "T4-600-2",
    "T4-600-3"
  ],
  "T4-605-2": [
    "T4-600-2",
    "T4-600-3"
  ],
  "T4-606-2": [
    "T4-600-3",
    "T4-600-2"
  ],
  "T4-606-1": [
    "T4-600-3",
    "T4-600-2"
  ],
  "T4-607": [
    "T4-600-3",
    "T4-600-2"
  ],
  "T4-WCM-6F": [
    "T4-600-3",
    "T4-600-2"
  ],
  "T4-WCF-6F": [
    "T4-600-2",
    "T4-600-3"
  ],
  "RB-WCF-6F": [
    "RB-600-1",
    "RB-600-4"
  ],
  "RB-WCM-6F": [
    "RB-600-4",
    "RB-600-1"
  ],
  "RB-604": [
    "RB-600-6",
    "RB-600-5"
  ],
  "RB-606": [
    "RB-600-4",
    "RB-600-5"
  ],
  "RB-609-1": [
    "RB-600-2",
    "RB-600-3"
  ],
  "RB-607": [
    "RB-600-1",
    "RB-600-2"
  ],
  "RB-608": [
    "RB-600-3",
    "RB-600-2"
  ],
  "RB-609": [
    "RB-600-3",
    "RB-600-2"
  ],
  "RB-610": [
    "RB-600-2",
    "RB-600-1"
  ],
  "T4-704-1": [
    "T4-700-2",
    "T4-700-3"
  ],
  "T4-704-2": [
    "T4-700-2",
    "T4-700-3"
  ],
  "T4-705-1": [
    "T4-700-2",
    "T4-700-3"
  ],
  "T4-707": [
    "T4-700-3",
    "T4-700-4"
  ],
  "T4-708": [
    "T4-700-4",
    "T4-700-3"
  ],
  "T4-711": [
    "T4-700-3",
    "T4-700-4"
  ],
  "RB-Stack-8F": [
    "RB-Stack-800-1",
    "RB-Stack-800-2"
  ],
  "T4-WCM-7F": [
    "T4-700-3",
    "T4-700-2"
  ],
  "T4-WCF-7F": [
    "T4-700-3",
    "T4-700-2"
  ],
  "T4-712": [
    "T4-700-4",
    "T4-700-3"
  ],
  "T4-713": [
    "T4-700-4",
    "T4-700-3"
  ],
  "T4-714": [
    "T4-700-4",
    "T4-700-3"
  ],
  "T4-715": [
    "T4-700-4",
    "T4-700-3"
  ],
  "T4-716": [
    "T4-700-4",
    "T4-700-3"
  ],
  "T4-717": [
    "T4-700-4",
    "T4-700-3"
  ],
  "T4-709": [
    "T4-700-4",
    "T4-700-3"
  ],
  "T4-710": [
    "T4-700-4",
    "T4-700-3"
  ],
  "T4-705-2": [
    "T4-700-2",
    "T4-700-3"
  ],
  "T4-703-2": [
    "T4-700-2",
    "T4-700-3"
  ],
  "T4-703-1": [
    "T4-700-1",
    "T4-700-2"
  ],
  "T4-702": [
    "T4-700-1",
    "T4-700-2"
  ],
  "T4-701-2": [
    "T4-700-1",
    "T4-700-2"
  ],
  "T4-701-1": [
    "T4-700-1",
    "T4-700-2"
  ],
  "RB-610-1": [
    "RB-600-2",
    "RB-600-1"
  ],
  "RB-601": [
    "RB-600-5",
    "RB-600-4"
  ],
  "RB-602": [
    "RB-600-5",
    "RB-600-6"
  ],
  "RB-605": [
    "RB-600-5",
    "RB-600-4"
  ],
  "RB-605-1": [
    "RB-600-5",
    "RB-600-6"
  ],
  "RB-603": [
    "RB-600-6",
    "RB-600-5"
  ],
  "RB-601-1": [
    "RB-600-4",
    "RB-600-1"
  ],
  "T4-WCM-8F": [
    "T4-800-4",
    "T4-800-3"
  ],
  "T4-WCF-8F": [
    "T4-800-4",
    "T4-800-3"
  ],
  "T4-837": [
    "T4-800-5",
    "T4-800-4"
  ],
  "T4-836-2": [
    "T4-800-5",
    "T4-800-4"
  ],
  "T4-836-1": [
    "T4-800-5",
    "T4-800-4"
  ],
  "T4-835": [
    "T4-800-4",
    "T4-800-5"
  ],
  "T4-834": [
    "T4-800-5",
    "T4-800-4"
  ],
  "T4-832": [
    "T4-800-4",
    "T4-800-5"
  ],
  "T4-831": [
    "T4-800-4",
    "T4-800-3"
  ],
  "T4-824": [
    "T4-800-2",
    "T4-800-3"
  ],
  "T4-822": [
    "T4-800-2",
    "T4-800-1"
  ],
  "T4-820": [
    "T4-800-2",
    "T4-800-1"
  ],
  "T4-818": [
    "T4-800-1",
    "T4-800-2"
  ],
  "T4-816": [
    "T4-800-1",
    "T4-800-2"
  ],
  "T4-811": [
    "T4-800-2",
    "T4-800-3"
  ],
  "T4-807": [
    "T4-800-2",
    "T4-800-1"
  ],
  "T4-805": [
    "T4-800-2",
    "T4-800-1"
  ],
  "T4-803": [
    "T4-800-1",
    "T4-800-2"
  ],
  "T4-801": [
    "T4-800-1",
    "T4-800-2"
  ],
  "RB-707": [
    "RB-700-5",
    "RB-700-4"
  ],
  "RB-704": [
    "RB-700-6",
    "RB-700-5"
  ],
  "RB-WCF-7F": [
    "RB-700-1",
    "RB-700-4"
  ],
  "RB-WCM-7F": [
    "RB-700-4",
    "RB-700-1"
  ],
  "RB-708": [
    "RB-700-2",
    "RB-700-1"
  ],
  "RB-709": [
    "RB-700-2",
    "RB-700-3"
  ],
  "RB-710": [
    "RB-700-3",
    "RB-700-2"
  ],
  "RB-711": [
    "RB-700-1",
    "RB-700-2"
  ],
  "RB-701": [
    "RB-700-5",
    "RB-700-4"
  ],
  "RB-702": [
    "RB-700-5",
    "RB-700-4"
  ],
  "RB-703": [
    "RB-700-5",
    "RB-700-4"
  ],
  "RB-705": [
    "RB-700-6",
    "RB-700-5"
  ],
  "RB-701-1": [
    "RB-700-4",
    "RB-700-1"
  ],
  "RB-706-1": [
    "RB-700-5",
    "RB-700-6"
  ],
  "RB-706-2": [
    "RB-700-6",
    "RB-700-5"
  ],
  "T4-802": [
    "T4-800-1",
    "T4-800-2"
  ],
  "T4-804": [
    "T4-800-2",
    "T4-800-1"
  ],
  "T4-806": [
    "T4-800-2",
    "T4-800-1"
  ],
  "T4-808": [
    "T4-800-2",
    "T4-800-1"
  ],
  "T4-809": [
    "T4-800-2",
    "T4-800-3"
  ],
  "T4-810": [
    "T4-800-2",
    "T4-800-3"
  ],
  "T4-812": [
    "T4-800-3",
    "T4-800-2"
  ],
  "T4-813": [
    "T4-800-3",
    "T4-800-4"
  ],
  "T4-814": [
    "T4-800-3",
    "T4-800-4"
  ],
  "T4-815": [
    "T4-800-3",
    "T4-800-4"
  ],
  "T4-817": [
    "T4-800-1",
    "T4-800-2"
  ],
  "T4-819": [
    "T4-800-2",
    "T4-800-1"
  ],
  "T4-821": [
    "T4-800-2",
    "T4-800-1"
  ],
  "T4-823": [
    "T4-800-2",
    "T4-800-1"
  ],
  "T4-825": [
    "T4-800-2",
    "T4-800-3"
  ],
  "T4-826": [
    "T4-800-2",
    "T4-800-3"
  ],
  "T4-827": [
    "T4-800-3",
    "T4-800-2"
  ],
  "T4-828": [
    "T4-800-3",
    "T4-800-4"
  ],
  "T4-829": [
    "T4-800-3",
    "T4-800-4"
  ],
  "T4-830": [
    "T4-800-3",
    "T4-800-4"
  ],
  "T4-833": [
    "T4-800-5",
    "T4-800-4"
  ],
  "T4-831-1": [
    "T4-800-3",
    "T4-800-4"
  ],
  "RB-810-2": [
    "RB-800-3",
    "RB-800-2"
  ],
  "RB-810-1": [
    "RB-800-3",
    "RB-800-2"
  ],
  "RB-809-B": [
    "RB-800-2",
    "RB-800-1"
  ],
  "RB-809-A": [
    "RB-800-2",
    "RB-800-1"
  ],
  "RB-801": [
    "RB-800-4",
    "RB-800-5"
  ],
  "RB-WCF-8F": [
    "RB-800-1",
    "RB-800-4"
  ],
  "RB-WCM-8F": [
    "RB-800-4",
    "RB-800-1"
  ],
  "RB-808": [
    "RB-800-5",
    "RB-800-4"
  ],
  "RB-802": [
    "RB-800-4",
    "RB-800-5"
  ],
  "RB-803": [
    "RB-800-5",
    "RB-800-6"
  ],
  "RB-804": [
    "RB-800-5",
    "RB-800-6"
  ],
  "RB-805": [
    "RB-800-6",
    "RB-800-5"
  ],
  "RB-806": [
    "RB-800-6",
    "RB-800-5"
  ],
  "RB-807": [
    "RB-800-5",
    "RB-800-6"
  ],
  "RB-801-1": [
    "RB-800-4",
    "RB-800-1"
  ],
  "RB-WCF-9F": [
    "RB-900-1",
    "RB-900-4"
  ],
  "RB-WCM-9F": [
    "RB-900-4",
    "RB-900-1"
  ],
  "RB-906": [
    "RB-900-5",
    "RB-900-6"
  ],
  "RB-907": [
    "RB-900-5",
    "RB-900-4"
  ],
  "RB-908": [
    "RB-900-4",
    "RB-900-5"
  ],
  "RB-905": [
    "RB-900-6",
    "RB-900-5"
  ],
  "RB-909-1": [
    "RB-900-1",
    "RB-900-2"
  ],
  "RB-909-2": [
    "RB-900-2",
    "RB-900-3"
  ],
  "RB-910-1": [
    "RB-900-2",
    "RB-900-3"
  ],
  "RB-910-2": [
    "RB-900-3",
    "RB-900-2"
  ],
  "RB-912-1": [
    "RB-900-1",
    "RB-900-2"
  ],
  "RB-912-2": [
    "RB-900-2",
    "RB-900-3"
  ],
  "RB-911-1": [
    "RB-900-2",
    "RB-900-3"
  ],
  "RB-911-2": [
    "RB-900-3",
    "RB-900-2"
  ],
  "RB-913": [
    "RB-900-1",
    "RB-900-4"
  ],
  "RB-914": [
    "RB-900-4",
    "RB-900-1"
  ],
  "RB-901": [
    "RB-900-4",
    "RB-900-5"
  ],
  "RB-902": [
    "RB-900-4",
    "RB-900-5"
  ],
  "RB-903": [
    "RB-900-5",
    "RB-900-6"
  ],
  "RB-904": [
    "RB-900-5",
    "RB-900-6"
  ],
  "AU-100-1": [
    "T4-100-2"
  ]
}